keyring_minimal/__init__.py
keyring_minimal/__main__.py
keyring_minimal-0.1.dist-info/LICENSE
keyring_minimal-0.1.dist-info/METADATA
keyring_minimal-0.1.dist-info/WHEEL
keyring_minimal-0.1.dist-info/entry_points.txt
keyring_minimal-0.1.dist-info/top_level.txt
keyring_minimal-0.1.dist-info/RECORD
